pytest_max_warnings/__init__.py
pytest_max_warnings/plugin.py
pytest_max_warnings/py.typed
pytest_max_warnings-0.1.0.dist-info/METADATA
pytest_max_warnings-0.1.0.dist-info/WHEEL
pytest_max_warnings-0.1.0.dist-info/entry_points.txt
pytest_max_warnings-0.1.0.dist-info/licenses/LICENSE
pytest_max_warnings-0.1.0.dist-info/RECORD
